secretmanager/__init__.py
secretmanager/error_helper.py
secretmanager/secret_manager.py
secretmanager/utils.py
secret_manager-0.0.3.dist-info/METADATA
secret_manager-0.0.3.dist-info/WHEEL
secret_manager-0.0.3.dist-info/top_level.txt
secret_manager-0.0.3.dist-info/RECORD
