Metadata-Version: 2.1
Name: secret-manager
Version: 0.0.3
Summary: Secret Manager AWS
Home-page: UNKNOWN
Author: Praveen Kumar
Author-email: praveen.k@blackbuck.com
License: MIT
Platform: UNKNOWN
